aind_sharepoint_service_async_client/__init__.py
aind_sharepoint_service_async_client/api_client.py
aind_sharepoint_service_async_client/api_response.py
aind_sharepoint_service_async_client/configuration.py
aind_sharepoint_service_async_client/exceptions.py
aind_sharepoint_service_async_client/py.typed
aind_sharepoint_service_async_client/rest.py
aind_sharepoint_service_async_client/api/__init__.py
aind_sharepoint_service_async_client/api/default_api.py
aind_sharepoint_service_async_client/api/healthcheck_api.py
aind_sharepoint_service_async_client/models/__init__.py
aind_sharepoint_service_async_client/models/health_check.py
aind_sharepoint_service_async_client/models/http_validation_error.py
aind_sharepoint_service_async_client/models/las2020_list.py
aind_sharepoint_service_async_client/models/las_bctype.py
aind_sharepoint_service_async_client/models/las_deliverylocation.py
aind_sharepoint_service_async_client/models/las_doseroute.py
aind_sharepoint_service_async_client/models/las_icvlims.py
aind_sharepoint_service_async_client/models/las_icvroute1.py
aind_sharepoint_service_async_client/models/las_icvroute2.py
aind_sharepoint_service_async_client/models/las_icvroute3.py
aind_sharepoint_service_async_client/models/las_icvroute4.py
aind_sharepoint_service_async_client/models/las_icvroute5.py
aind_sharepoint_service_async_client/models/las_limsproject.py
aind_sharepoint_service_async_client/models/las_limsworkflow.py
aind_sharepoint_service_async_client/models/las_limsworkflow2.py
aind_sharepoint_service_async_client/models/las_postfix.py
aind_sharepoint_service_async_client/models/las_projectid.py
aind_sharepoint_service_async_client/models/las_protocol.py
aind_sharepoint_service_async_client/models/las_reqpro1.py
aind_sharepoint_service_async_client/models/las_reqpro2.py
aind_sharepoint_service_async_client/models/las_reqpro3.py
aind_sharepoint_service_async_client/models/las_reqpro4.py
aind_sharepoint_service_async_client/models/las_requeststatus2.py
aind_sharepoint_service_async_client-0.1.5.dist-info/METADATA
aind_sharepoint_service_async_client-0.1.5.dist-info/WHEEL
aind_sharepoint_service_async_client-0.1.5.dist-info/top_level.txt
aind_sharepoint_service_async_client-0.1.5.dist-info/RECORD
